vcver/__init__.py
vcver/exception.py
vcver/version.py
vcver/version_string.py
vcver/scm/__init__.py
vcver/scm/base.py
vcver/scm/git.py
vcver/scm/mock.py
vcver/tests/__init__.py
vcver/tests/test_full.py
vcver/tests/test_version.py
vcver/tests/test_version_string.py
vcver/tests/scm/__init__.py
vcver/tests/scm/conftest.py
vcver/tests/scm/test_base.py
vcver/tests/scm/test_git.py
vcver-0.2.12.dist-info/LICENSE
vcver-0.2.12.dist-info/METADATA
vcver-0.2.12.dist-info/WHEEL
vcver-0.2.12.dist-info/entry_points.txt
vcver-0.2.12.dist-info/top_level.txt
vcver-0.2.12.dist-info/RECORD
